<?xml version="1.0" encoding="utf-8"?>
<UNI_BSS_BODY>
    <SYN_RES_RSP mappedOut="true">
        <RESP_CODE constraint="1" length="F4" mappedName="code">
        </RESP_CODE>
        <RESP_DESC constraint="?" length="V500" mappedName="detail">
        </RESP_DESC> 
        <PARA constraint="*" mappedName="para">
            <PARA_ID constraint="1" length="V20" mappedName="paraId" />
            <PARA_VALUE constraint="1" length="V60" mappedName="paraValue" />
        </PARA>
    </SYN_RES_RSP>
</UNI_BSS_BODY>